MANIFEST.in
README.txt
setup.cfg
setup.py
docs/HISTORY.txt
docs/INSTALL.txt
docs/LICENSE.GPL
docs/LICENSE.txt
redomino/__init__.py
redomino/__init__.pyc
redomino.breadcrumbsbrain.egg-info/PKG-INFO
redomino.breadcrumbsbrain.egg-info/SOURCES.txt
redomino.breadcrumbsbrain.egg-info/dependency_links.txt
redomino.breadcrumbsbrain.egg-info/entry_points.txt
redomino.breadcrumbsbrain.egg-info/namespace_packages.txt
redomino.breadcrumbsbrain.egg-info/not-zip-safe
redomino.breadcrumbsbrain.egg-info/requires.txt
redomino.breadcrumbsbrain.egg-info/top_level.txt
redomino/breadcrumbsbrain/__init__.py
redomino/breadcrumbsbrain/breadcrumbs.py
redomino/breadcrumbsbrain/configure.zcml
redomino/breadcrumbsbrain/interfaces.py
redomino/breadcrumbsbrain/tests.py
redomino/breadcrumbsbrain/locales/redomino.breadcrumbsbrain.pot
redomino/breadcrumbsbrain/locales/update.sh
redomino/breadcrumbsbrain/locales/it/LC_MESSAGES/redomino.breadcrumbsbrain.po
redomino/breadcrumbsbrain/templates/breadcrumbs_renderer.pt