Metadata-Version: 1.0
Name: redomino.breadcrumbsbrain
Version: 0.4
Summary: Breadcrumbs for brains
Home-page: https://github.com/redomino/redomino.breadcrumbsbrain
Author: Davide Moro
Author-email: davide.moro@redomino.com
License: GPL
Keywords: Plone
Platform: UNKNOWN
Classifier: Framework :: Plone
Classifier: Programming Language :: Python
Classifier: License :: OSI Approved :: GNU General Public License (GPL)
